html2pdfconverter/__init__.py
html2pdfconverter/client.py
html2pdfconverter-0.1.0.dist-info/METADATA
html2pdfconverter-0.1.0.dist-info/WHEEL
html2pdfconverter-0.1.0.dist-info/top_level.txt
html2pdfconverter-0.1.0.dist-info/RECORD
