Metadata-Version: 2.4
Name: html2pdfconverter
Version: 0.1.0
Summary: Python SDK for html2pdfconverter.com
Author: HTML2PDFConverter
License: MIT
Project-URL: Homepage, https://www.html2pdfconverter.com
Project-URL: Documentation, https://html2pdfconverter.com/docs
Project-URL: Repository, https://github.com/html2pdfconverter/html2pdf-python
Project-URL: Issues, https://github.com/html2pdfconverter/html2pdf-python/issues
Requires-Python: >=3.8
Requires-Dist: requests>=2.31.0
Provides-Extra: dev
Requires-Dist: pytest>=7.0.0; extra == "dev"
Requires-Dist: pytest-mock>=3.10.0; extra == "dev"
